LICENSE
README.md
setup.py
./setup.py
./coti/__init__.py
./coti/crypto_utils.py
./coti/types.py
coti_sdk.egg-info/PKG-INFO
coti_sdk.egg-info/SOURCES.txt
coti_sdk.egg-info/dependency_links.txt
coti_sdk.egg-info/requires.txt
coti_sdk.egg-info/top_level.txt