Metadata-Version: 2.1
Name: coti_sdk
Version: 1.0.3
Summary: COTI SDK for Privacy Preserving Network
Home-page: https://github.com/coti-io/coti-sdk-python
Author: gmesika-coti@COTI
Author-email: support@coti.io
License: Apache2.0
Keywords: COTI SDK Privacy
Requires-Python: >=3.9
License-File: LICENSE
Requires-Dist: pycryptodome==3.19.0
Requires-Dist: cryptography==3.4.8
Requires-Dist: eth-keys>=0.4.0
Requires-Dist: eth-account>=0.13.1
